logitfunction/__init__.py
logitfunction/__main__.py
logitfunction/core/__init__.py
logitfunction/tests/__init__.py
logitfunction/tests/test_1984.py
logitfunction-0.0.2.dist-info/LICENSE.txt
logitfunction-0.0.2.dist-info/METADATA
logitfunction-0.0.2.dist-info/WHEEL
logitfunction-0.0.2.dist-info/top_level.txt
logitfunction-0.0.2.dist-info/RECORD
