Metadata-Version: 2.2
Name: logitfunction
Version: 0.0.2
Summary: This projects implements the logit function.
Author-email: Johannes <johannes-programming@mailfence.com>
License: The MIT License (MIT)
Project-URL: Download, https://pypi.org/project/logitfunction/#files
Project-URL: Index, https://pypi.org/project/logitfunction/
Project-URL: Source, https://github.com/johannes-programming/logitfunction/
Project-URL: Website, https://logitfunction.johannes-programming.online/
Classifier: Development Status :: 2 - Pre-Alpha
Classifier: License :: OSI Approved :: MIT License
Classifier: Natural Language :: English
Classifier: Operating System :: OS Independent
Classifier: Programming Language :: Python
Classifier: Programming Language :: Python :: 3
Classifier: Programming Language :: Python :: 3 :: Only
Classifier: Typing :: Typed
Requires-Python: >=3.8
License-File: LICENSE.txt
